markdown_converter_1/__init__.py
markdown_converter_1/converter_core.py
mark_2_pdf-0.1.1.dist-info/METADATA
mark_2_pdf-0.1.1.dist-info/WHEEL
mark_2_pdf-0.1.1.dist-info/top_level.txt
mark_2_pdf-0.1.1.dist-info/RECORD
