Metadata-Version: 2.4
Name: mark-2-pdf
Version: 0.1.1
Summary: A Python package for converting Markdown content or files to PDF (Playwright) or DOCX (Pandoc).
Author-email: Mokksh Kapur <mokkshkapur@gmail.com>
License: MIT License
Project-URL: Homepage, https://github.com/Mokkshkapur
Keywords: markdown,pdf,docx,converter,pandoc,playwright,document,conversion,utility
Classifier: Programming Language :: Python :: 3
Classifier: Programming Language :: Python :: 3.7
Classifier: Programming Language :: Python :: 3.8
Classifier: Programming Language :: Python :: 3.9
Classifier: Programming Language :: Python :: 3.10
Classifier: Programming Language :: Python :: 3.11
Classifier: Programming Language :: Python :: 3.12
Classifier: License :: OSI Approved :: MIT License
Classifier: Operating System :: OS Independent
Classifier: Topic :: Text Processing :: Markup
Classifier: Topic :: Utilities
Classifier: Topic :: Office/Business :: Office Suites
Classifier: Development Status :: 3 - Alpha
Classifier: Intended Audience :: Developers
Requires-Python: >=3.7
Requires-Dist: Markdown>3.3
Requires-Dist: playwright>=1.20
Requires-Dist: Pygments>=2.9
